README.md
setup.py
curseXcel/__init__.py
curseXcel/curseXcel.py
curseXcel.egg-info/PKG-INFO
curseXcel.egg-info/SOURCES.txt
curseXcel.egg-info/dependency_links.txt
curseXcel.egg-info/top_level.txt