Metadata-Version: 1.0
Name: curseXcel
Version: 0.0.1
Summary: ncurses library to generate and manipulate tables
Home-page: http://github.com/coffeeandscripts/curseXcel
Author: coffeeandscripts
Author-email: coffeeandscripts@gmail.com
License: GNU
Platform: UNKNOWN
